DynamicDnsUpdater/AddressInfo.py
DynamicDnsUpdater/DynamicDnsUpdater.py
DynamicDnsUpdater/IpDnsPoller.py
DynamicDnsUpdater/NetworkAdapter.py
DynamicDnsUpdater/NetworkHookHandler.py
DynamicDnsUpdater/Registry.py
DynamicDnsUpdater/Resolve.py
DynamicDnsUpdater/__init__.py
DynamicDnsUpdater/objects.py
DynamicDnsUpdater/version.py
pyDynamicDnsUpdater-1.0.0a16.dist-info/LICENSE
pyDynamicDnsUpdater-1.0.0a16.dist-info/METADATA
pyDynamicDnsUpdater-1.0.0a16.dist-info/WHEEL
pyDynamicDnsUpdater-1.0.0a16.dist-info/top_level.txt
pyDynamicDnsUpdater-1.0.0a16.dist-info/RECORD
