Metadata-Version: 2.1
Name: pyDynamicDnsUpdater
Version: 1.0.0a16
Summary: A Python library to modify and alter the dns records in according to configuration passed
Home-page: https://github.com/iktdev-no/pyDynamicDnsUpdater
Author: Brage Skjønborg
Author-email: bskjon@outlook.com
Classifier: Intended Audience :: Developers
Classifier: Operating System :: POSIX :: Linux
Classifier: Programming Language :: Python
Classifier: Programming Language :: Python :: 3
Classifier: Topic :: System :: Networking
Classifier: Topic :: Software Development :: Libraries :: Python Modules
Requires-Python: >=3.9.0
License-File: LICENSE
Requires-Dist: netifaces>=0.11.0
Requires-Dist: netaddr>=0.8.0
Requires-Dist: dnspython>=2.4.0
Requires-Dist: domeneshop>=0.4.3
Requires-Dist: tldextract>=5.1.2
